Workbook
Name CHECK: CHECK!$C$10

Sheet CM01_23.06.2026_PC_001
A1: DOCUMENT HEADER DATA | J1: DOCUMENT LINE ITEM DATA | AI1: AP Only | AO1: Onetime Only | AV1: CARBON ACCOUNTING
A2: LI. | B2: Comp. Code | C2: Doc. Type | D2: Post | E2: Doc. Date | F2: Curr | G2: Ref. | H2: Doc. Header Text | I2: Tax Calculation | J2: Account (GL Account or Vendor or Customer Code) | K2: Post | L2: Amount | M2: Tax Code | N2: Assig | O2: Cost Center | P2: Internal Order | Q2: Trading Partner | R2: Partner Profit Center | S2: Profit Centre | T2: Rever.reason | U2: Revers | V2: Item Text | W2: Sales Center | X2: Billing type | Y2: Direction | Z2: Material | AA2: Plant | AB2: Warehouse | AC2: Customer | AD2: 3rdP/IC WWI_C | AE2: Reference 1 | AF2: Reference 2 | AG2: Reference 3 | AH2: Transaction Type | AI2: Payment Term | AJ2: Baseline Date | AK2: Payment Method | AL2: Payment Block | AM2: Business Place | AN2: Business Section | AO2: Name 1 | AP2: Name 3 | AQ2: City | AR2: Bank Key | AS2: Bank Account | AT2: Control Key | AU2: Instruction key | AV2: Quantity | AW2: Unit of Measure
D3: Date | G3: Doc. Nr | K3: Key | L3: =CHECK | S3: FR0100 | U3: Date

Sheet BANK DETAILS 
A1: Company Code | B1: Fiscal year/period | C1: Group Account Number | D1: G/L Account | E1: G/L Account: Long Text | F1: Posting Date | G1: Document Date | H1: Reference | I1: Assignment | J1: Text | K1: Posting Key | L1: Company Code Currency Value | M1: Company Code Currency Key | N1: Document Currency Value | O1: Currency | P1: Group Currency Value | Q1: Group Currency Key | R1: Document Type | S1: Document Number | T1: Item | U1: Offsetting Account | V1: User Name | W1: Entry Date | X1: Clearing Document | Y1: Document Currency Key | Z1: Clearing Entry Date | AA1: Clearing Date | AB1: Accounting Indicator | AC1: Transaction Type | AD1: Document Header Text | AE1: Transaction Type | AF1: Year | AG1: Offsetting Account Type | AH1: Cost Center | AI1: Reversal Reason | AJ1: Purchasing Document | AK1: Profit Center | AL1: Posting Period | AM1: Name | AN1: Discount Lne Iem | AO1: Invoice Reference

Sheet Sheet1

Sheet CHECK
A2: Nature | B2: Posting KEY | C2: Amount | D2: Item
A3: Debit | B3: 01 | C3: =SUMIF('CM01_23.06.2026_PC_001'!K:K,CHECK!B3,'CM01_23.06.2026_PC_001'!L:L) | D3: Customer ( AR )
A4: Debit | B4: 21 | C4: =SUMIF('CM01_23.06.2026_PC_001'!K:K,CHECK!B4,'CM01_23.06.2026_PC_001'!L:L) | D4: Vendor ( AP )
A5: Debit | B5: 40 | C5: =SUMIF('CM01_23.06.2026_PC_001'!K:K,CHECK!B5,'CM01_23.06.2026_PC_001'!L:L) | D5: GL
A6: Credit | B6: 11 | C6: =-SUMIF('CM01_23.06.2026_PC_001'!K:K,CHECK!B6,'CM01_23.06.2026_PC_001'!L:L) | D6: Customer ( AR )
A7: Credit | B7: 15 | C7: =-SUMIF('CM01_23.06.2026_PC_001'!K:K,CHECK!B7,'CM01_23.06.2026_PC_001'!L:L) | D7: Customer ( AR )
A8: Credit | B8: 31 | C8: =-SUMIF('CM01_23.06.2026_PC_001'!K:K,CHECK!B8,'CM01_23.06.2026_PC_001'!L:L) | D8: Vendor ( AP )
A9: Credit | B9: 50 | C9: =-SUMIF('CM01_23.06.2026_PC_001'!K:K,CHECK!B9,'CM01_23.06.2026_PC_001'!L:L) | D9: GL
C10: =ROUND(SUM(C3:C9),3)

Sheet Doc Level Check
A1: Doc. Header Text | C1: 50 | D1: 40
B2: =COUNTIF('CM01_23.06.2026_PC_001'!H:H,'Doc Level Check'!A2) | C2: =SUMIFS('CM01_23.06.2026_PC_001'!L:L,'CM01_23.06.2026_PC_001'!H:H,'Doc Level Check'!A2,'CM01_23.06.2026_PC_001'!K:K,'Doc Level Check'!$C$1) | D2: =SUMIFS('CM01_23.06.2026_PC_001'!L:L,'CM01_23.06.2026_PC_001'!H:H,'Doc Level Check'!A2,'CM01_23.06.2026_PC_001'!K:K,'Doc Level Check'!$D$1) | E2: =C2-D2
B3: =COUNTIF('CM01_23.06.2026_PC_001'!H:H,'Doc Level Check'!A3) | C3: =SUMIFS('CM01_23.06.2026_PC_001'!L:L,'CM01_23.06.2026_PC_001'!H:H,'Doc Level Check'!A3,'CM01_23.06.2026_PC_001'!K:K,'Doc Level Check'!$C$1) | D3: =SUMIFS('CM01_23.06.2026_PC_001'!L:L,'CM01_23.06.2026_PC_001'!H:H,'Doc Level Check'!A3,'CM01_23.06.2026_PC_001'!K:K,'Doc Level Check'!$D$1) | E3: =C3-D3
B4: =COUNTIF('CM01_23.06.2026_PC_001'!H:H,'Doc Level Check'!A4) | C4: =SUMIFS('CM01_23.06.2026_PC_001'!L:L,'CM01_23.06.2026_PC_001'!H:H,'Doc Level Check'!A4,'CM01_23.06.2026_PC_001'!K:K,'Doc Level Check'!$C$1) | D4: =SUMIFS('CM01_23.06.2026_PC_001'!L:L,'CM01_23.06.2026_PC_001'!H:H,'Doc Level Check'!A4,'CM01_23.06.2026_PC_001'!K:K,'Doc Level Check'!$D$1) | E4: =C4-D4
B5: =COUNTIF('CM01_23.06.2026_PC_001'!H:H,'Doc Level Check'!A5) | C5: =SUMIFS('CM01_23.06.2026_PC_001'!L:L,'CM01_23.06.2026_PC_001'!H:H,'Doc Level Check'!A5,'CM01_23.06.2026_PC_001'!K:K,'Doc Level Check'!$C$1) | D5: =SUMIFS('CM01_23.06.2026_PC_001'!L:L,'CM01_23.06.2026_PC_001'!H:H,'Doc Level Check'!A5,'CM01_23.06.2026_PC_001'!K:K,'Doc Level Check'!$D$1) | E5: =C5-D5
B6: =COUNTIF('CM01_23.06.2026_PC_001'!H:H,'Doc Level Check'!A6) | C6: =SUMIFS('CM01_23.06.2026_PC_001'!L:L,'CM01_23.06.2026_PC_001'!H:H,'Doc Level Check'!A6,'CM01_23.06.2026_PC_001'!K:K,'Doc Level Check'!$C$1) | D6: =SUMIFS('CM01_23.06.2026_PC_001'!L:L,'CM01_23.06.2026_PC_001'!H:H,'Doc Level Check'!A6,'CM01_23.06.2026_PC_001'!K:K,'Doc Level Check'!$D$1) | E6: =C6-D6
B7: =COUNTIF('CM01_23.06.2026_PC_001'!H:H,'Doc Level Check'!A7) | C7: =SUMIFS('CM01_23.06.2026_PC_001'!L:L,'CM01_23.06.2026_PC_001'!H:H,'Doc Level Check'!A7,'CM01_23.06.2026_PC_001'!K:K,'Doc Level Check'!$C$1) | D7: =SUMIFS('CM01_23.06.2026_PC_001'!L:L,'CM01_23.06.2026_PC_001'!H:H,'Doc Level Check'!A7,'CM01_23.06.2026_PC_001'!K:K,'Doc Level Check'!$D$1) | E7: =C7-D7
B8: =COUNTIF('CM01_23.06.2026_PC_001'!H:H,'Doc Level Check'!A8) | C8: =SUMIFS('CM01_23.06.2026_PC_001'!L:L,'CM01_23.06.2026_PC_001'!H:H,'Doc Level Check'!A8,'CM01_23.06.2026_PC_001'!K:K,'Doc Level Check'!$C$1) | D8: =SUMIFS('CM01_23.06.2026_PC_001'!L:L,'CM01_23.06.2026_PC_001'!H:H,'Doc Level Check'!A8,'CM01_23.06.2026_PC_001'!K:K,'Doc Level Check'!$D$1) | E8: =C8-D8
B9: =COUNTIF('CM01_23.06.2026_PC_001'!H:H,'Doc Level Check'!A9) | C9: =SUMIFS('CM01_23.06.2026_PC_001'!L:L,'CM01_23.06.2026_PC_001'!H:H,'Doc Level Check'!A9,'CM01_23.06.2026_PC_001'!K:K,'Doc Level Check'!$C$1) | D9: =SUMIFS('CM01_23.06.2026_PC_001'!L:L,'CM01_23.06.2026_PC_001'!H:H,'Doc Level Check'!A9,'CM01_23.06.2026_PC_001'!K:K,'Doc Level Check'!$D$1) | E9: =C9-D9
B10: =COUNTIF('CM01_23.06.2026_PC_001'!H:H,'Doc Level Check'!A10) | C10: =SUMIFS('CM01_23.06.2026_PC_001'!L:L,'CM01_23.06.2026_PC_001'!H:H,'Doc Level Check'!A10,'CM01_23.06.2026_PC_001'!K:K,'Doc Level Check'!$C$1) | D10: =SUMIFS('CM01_23.06.2026_PC_001'!L:L,'CM01_23.06.2026_PC_001'!H:H,'Doc Level Check'!A10,'CM01_23.06.2026_PC_001'!K:K,'Doc Level Check'!$D$1) | E10: =C10-D10

Sheet Fields
A1: LI.
A2: Comp. Code
A3: Doc. Type
A4: Posting Date
A5: Document Date
A6: Currency
A7: Refernce
A8: Doc. Header Text
A9: Tax Calculation
A10: Account (GL Account or Vendor / customerCode)
A11: Post
A12: Amount
... A36: Baseline Date
A37: Payment Method | D37: 01 | E37: Invoice | F37: Debit | G37: Customer
A38: Payment Block | D38: 11 | E38: Credit memo | F38: Credit | G38: Customer
A39: Business Place | D39: 31 | E39: Invoice | F39: Credit | G39: Vendor
A40: Business Section | D40: 21 | E40: Debit memo | F40: Debit | G40: Vendor
A41: Name 1 | D41: 40 | F41: Debit | G41: GL
A42: Name 3 | D42: 50 | F42: Credit | G42: GL
A43: City
A44: Bank Key
A45: Bank Account
A46: Control Key
A47: Instruction key
A48: Quantity
A49: Unit of Measure
